agentevents/__init__.py
agentevents/main.py
agentevents-0.1.3.dist-info/LICENSE
agentevents-0.1.3.dist-info/METADATA
agentevents-0.1.3.dist-info/WHEEL
agentevents-0.1.3.dist-info/top_level.txt
agentevents-0.1.3.dist-info/RECORD
