Metadata-Version: 2.1
Name: agentevents
Version: 0.1.3
Summary: Searchable events with colorful log output for agents.
Home-page: https://github.com/AutonomousResearchGroup/agentevents
Author: Moon
Author-email: shawmakesmagic@gmail.com
License: MIT
Classifier: Development Status :: 5 - Production/Stable
Classifier: Intended Audience :: Science/Research
Classifier: License :: OSI Approved :: MIT License
Classifier: Operating System :: POSIX :: Linux
Classifier: Programming Language :: Python :: 3
Classifier: Operating System :: MacOS :: MacOS X
Classifier: Operating System :: Microsoft :: Windows
License-File: LICENSE
Requires-Dist: agentmemory
Requires-Dist: rich
